chemml/__init__.py
chemml/chem/CoulMat.py
chemml/chem/Dragon.py
chemml/chem/RDKFP.py
chemml/chem/__init__.py
chemml/chem/local_features.py
chemml/chem/molecule.py
chemml/chem/magpie_python/__init__.py
chemml/chem/magpie_python/attributes/__init__.py
chemml/chem/magpie_python/attributes/generators/__init__.py
chemml/chem/magpie_python/attributes/generators/composition/APEAttributeGenerator.py
chemml/chem/magpie_python/attributes/generators/composition/ChargeDependentAttributeGenerator.py
chemml/chem/magpie_python/attributes/generators/composition/ElementFractionAttributeGenerator.py
chemml/chem/magpie_python/attributes/generators/composition/ElementPairPropertyAttributeGenerator.py
chemml/chem/magpie_python/attributes/generators/composition/ElementalPropertyAttributeGenerator.py
chemml/chem/magpie_python/attributes/generators/composition/GCLPAttributeGenerator.py
chemml/chem/magpie_python/attributes/generators/composition/IonicCompoundProximityAttributeGenerator.py
chemml/chem/magpie_python/attributes/generators/composition/IonicityAttributeGenerator.py
chemml/chem/magpie_python/attributes/generators/composition/MeredigAttributeGenerator.py
chemml/chem/magpie_python/attributes/generators/composition/StoichiometricAttributeGenerator.py
chemml/chem/magpie_python/attributes/generators/composition/ValenceShellAttributeGenerator.py
chemml/chem/magpie_python/attributes/generators/composition/YangOmegaAttributeGenerator.py
chemml/chem/magpie_python/attributes/generators/composition/__init__.py
chemml/chem/magpie_python/attributes/generators/crystal/APRDFAttributeGenerator.py
chemml/chem/magpie_python/attributes/generators/crystal/ChemicalOrderingAttributeGenerator.py
chemml/chem/magpie_python/attributes/generators/crystal/CoordinationNumberAttributeGenerator.py
chemml/chem/magpie_python/attributes/generators/crystal/CoulombMatrixAttributeGenerator.py
chemml/chem/magpie_python/attributes/generators/crystal/EffectiveCoordinationNumberAttributeGenerator.py
chemml-1.2.dist-info/LICENSE
chemml-1.2.dist-info/METADATA
chemml-1.2.dist-info/WHEEL
chemml-1.2.dist-info/top_level.txt
chemml-1.2.dist-info/RECORD
