Metadata-Version: 2.1
Name: chemml
Version: 1.2
Summary: A Machine Learning and Informatics Program Suite for the Chemical and Materials Sciences
Author: Mojtaba Haghighatlari, Johannes Hachmann
Author-email: mojtabah@buffalo.edu, hachmann@buffalo.edu
License: BSD-3C
Project-URL: Source, https://github.com/hachmannlab/chemml
Project-URL: url, https://hachmannlab.github.io/chemml/
Keywords: Machine Learning,Data Mining,Quantum Chemistry,Materials Science,Drug Discovery
Platform: UNKNOWN
Classifier: Development Status :: 4 - Beta
Classifier: Natural Language :: English
Classifier: Intended Audience :: Science/Research
Classifier: Programming Language :: Python :: 3
License-File: LICENSE
Requires-Dist: future
Requires-Dist: six
Requires-Dist: numpy
Requires-Dist: pandas
Requires-Dist: scipy
Requires-Dist: tensorflow
Requires-Dist: h5py
Requires-Dist: scikit-learn
Requires-Dist: matplotlib (>=1.5.1)
Requires-Dist: lxml
Requires-Dist: wget
Requires-Dist: seaborn
Requires-Dist: openpyxl
Requires-Dist: ipywidgets
Provides-Extra: docs
Requires-Dist: sphinx ; extra == 'docs'
Requires-Dist: sphinxcontrib-napoleon ; extra == 'docs'
Requires-Dist: sphinx-rtd-theme ; extra == 'docs'
Requires-Dist: numpydoc ; extra == 'docs'
Requires-Dist: nbsphinx ; extra == 'docs'
Provides-Extra: tests
Requires-Dist: pytest ; extra == 'tests'
Requires-Dist: pytest-cov ; extra == 'tests'
Requires-Dist: pytest-pep8 ; extra == 'tests'
Requires-Dist: tox ; extra == 'tests'
